grafix/__init__.py
grafix/cc.py
grafix/py.typed
grafix/api/__init__.py
grafix/api/__init__.pyi
grafix/api/_param_resolution.py
grafix/api/effects.py
grafix/api/export.py
grafix/api/layers.py
grafix/api/primitives.py
grafix/api/runner.py
grafix/core/__init__.py
grafix/core/effect_registry.py
grafix/core/font_resolver.py
grafix/core/geometry.py
grafix/core/layer.py
grafix/core/pipeline.py
grafix/core/primitive_registry.py
grafix/core/realize.py
grafix/core/realized_geometry.py
grafix/core/runtime_config.py
grafix/core/scene.py
grafix/core/effects/__init__.py
grafix/core/effects/affine.py
grafix/core/effects/buffer.py
grafix/core/effects/clip.py
grafix/core/effects/collapse.py
grafix/core/effects/dash.py
grafix/core/effects/displace.py
grafix/core/effects/drop.py
grafix/core/effects/extrude.py
grafix/core/effects/fill.py
grafix/core/effects/mirror.py
grafix/core/effects/mirror3d.py
grafix/core/effects/partition.py
grafix/core/effects/quantize.py
grafix/core/effects/relax.py
grafix/core/effects/repeat.py
grafix/core/effects/rotate.py
grafix/core/effects/scale.py
grafix/core/effects/subdivide.py
grafix/core/effects/translate.py
grafix/core/effects/trim.py
grafix/core/effects/twist.py
grafix/core/effects/util.py
grafix/core/effects/weave.py
grafix/core/effects/wobble.py
grafix/core/parameters/__init__.py
grafix/core/parameters/codec.py
grafix/core/parameters/context.py
grafix/core/parameters/effects.py
grafix/core/parameters/frame_params.py
grafix/core/parameters/invariants.py
grafix/core/parameters/key.py
grafix/core/parameters/labels.py
grafix/core/parameters/labels_ops.py
grafix/core/parameters/layer_style.py
grafix/core/parameters/merge_ops.py
grafix/core/parameters/meta.py
grafix/core/parameters/meta_ops.py
grafix/core/parameters/ordinals.py
grafix/core/parameters/persistence.py
grafix/core/parameters/prune_ops.py
grafix/core/parameters/reconcile.py
grafix/core/parameters/reconcile_ops.py
grafix/core/parameters/resolver.py
grafix/core/parameters/runtime.py
grafix-0.0.3.dist-info/licenses/LICENSE
grafix-0.0.3.dist-info/METADATA
grafix-0.0.3.dist-info/WHEEL
grafix-0.0.3.dist-info/top_level.txt
grafix-0.0.3.dist-info/RECORD
