Metadata-Version: 2.4
Name: grafix
Version: 0.0.3
Summary: Line-based geometry toolkit with chained effects and real-time preview.
License: MIT License
Classifier: Development Status :: 4 - Beta
Classifier: Intended Audience :: Developers
Classifier: License :: OSI Approved :: MIT License
Classifier: Programming Language :: Python :: 3
Classifier: Programming Language :: Python :: 3 :: Only
Classifier: Programming Language :: Python :: 3.12
Classifier: Topic :: Multimedia :: Graphics
Requires-Python: >=3.11
License-File: LICENSE
Requires-Dist: numpy
Requires-Dist: numba
Requires-Dist: shapely
Requires-Dist: pyclipper
Requires-Dist: moderngl
Requires-Dist: pyglet
Requires-Dist: imgui
Requires-Dist: fontPens
Requires-Dist: fontTools
Requires-Dist: PyOpenGL
Requires-Dist: PyOpenGL_accelerate
Requires-Dist: PyYAML
Requires-Dist: mido
Requires-Dist: python-rtmidi
Requires-Dist: psutil
Provides-Extra: dev
Requires-Dist: pytest; extra == "dev"
Requires-Dist: ruff; extra == "dev"
Requires-Dist: mypy; extra == "dev"
Dynamic: license-file
